logsage/__init__.py
logsage/auto_resume_policy/README.md
logsage/auto_resume_policy/attribution_classes.py
logsage/auto_resume_policy/config.py
logsage/auto_resume_policy/consts.py
logsage/auto_resume_policy/error_attribution.py
logsage/auto_resume_policy/error_extraction.py
logsage/auto_resume_policy/log_sage.py
logsage/auto_resume_policy/main.py
logsage/auto_resume_policy/prompts.py
logsage/auto_resume_policy/utils.py
logsage-0.1.5.dist-info/LICENSE-3rd-party.txt
logsage-0.1.5.dist-info/LICENSE.txt
logsage-0.1.5.dist-info/METADATA
logsage-0.1.5.dist-info/WHEEL
logsage-0.1.5.dist-info/RECORD
