Metadata-Version: 2.3
Name: logsage
Version: 0.1.5
Summary: LLM-based library for AI training job failure attribution and recommending auto-resume policy
Author: Haim Elisha
Author-email: helisha@nvidia.com
Requires-Python: >=3.9,<4.0
Classifier: Development Status :: 3 - Alpha
Classifier: Intended Audience :: Developers
Classifier: License :: OSI Approved :: MIT License
Classifier: Operating System :: OS Independent
Classifier: Programming Language :: Python :: 3
Classifier: Programming Language :: Python :: 3.9
Classifier: Programming Language :: Python :: 3.10
Classifier: Programming Language :: Python :: 3.11
Classifier: Programming Language :: Python :: 3.12
Classifier: Programming Language :: Python :: 3.13
Requires-Dist: drain3 (>=0.9.11,<0.10.0)
Requires-Dist: langchain (>=0.3.27,<0.4.0)
Requires-Dist: langchain-core (>=0.3.0,<1.0.0)
Requires-Dist: langchain-nvidia-ai-endpoints (>=0.3.18,<0.4.0)
Requires-Dist: nh3 (>=0.3.1,<0.4.0)
Requires-Dist: numpy (<=2.0.2)
Requires-Dist: pandas (<=2.3.3)
Requires-Dist: pydantic-settings (>=2.11.0,<3.0.0)
Requires-Dist: requests (>=2.32.5,<3.0.0)
